cellprofiler_core/__init__.py
cellprofiler_core/__main__.py
cellprofiler_core/py.typed
cellprofiler_core/analysis/__init__.py
cellprofiler_core/analysis/_analysis.py
cellprofiler_core/analysis/_runner.py
cellprofiler_core/analysis/_worker_runner.py
cellprofiler_core/analysis/event/__init__.py
cellprofiler_core/analysis/event/_finished.py
cellprofiler_core/analysis/event/_paused.py
cellprofiler_core/analysis/event/_progress.py
cellprofiler_core/analysis/event/_resumed.py
cellprofiler_core/analysis/event/_started.py
cellprofiler_core/analysis/reply/__init__.py
cellprofiler_core/analysis/reply/_ack.py
cellprofiler_core/analysis/reply/_debug_cancel.py
cellprofiler_core/analysis/reply/_dictionary_request.py
cellprofiler_core/analysis/reply/_exception_please_debug.py
cellprofiler_core/analysis/reply/_image_set_success.py
cellprofiler_core/analysis/reply/_image_set_success_with_dictionary.py
cellprofiler_core/analysis/reply/_interaction.py
cellprofiler_core/analysis/reply/_no_work.py
cellprofiler_core/analysis/reply/_omero_login.py
cellprofiler_core/analysis/reply/_server_exited.py
cellprofiler_core/analysis/reply/_shared_dictionary.py
cellprofiler_core/analysis/reply/_work.py
cellprofiler_core/analysis/request/__init__.py
cellprofiler_core/analysis/request/_analysis_cancel.py
cellprofiler_core/analysis/request/_debug_complete.py
cellprofiler_core/analysis/request/_debug_waiting.py
cellprofiler_core/analysis/request/_display.py
cellprofiler_core/analysis/request/_display_post_group.py
cellprofiler_core/analysis/request/_display_post_run.py
cellprofiler_core/analysis/request/_exception_report.py
cellprofiler_core/analysis/request/_initial_measurements.py
cellprofiler_core/analysis/request/_interaction.py
cellprofiler_core/analysis/request/_measurements_report.py
cellprofiler_core/analysis/request/_omero_login.py
cellprofiler_core/analysis/request/_pipeline_preferences.py
cellprofiler_core/analysis/request/_shared_dictionary.py
cellprofiler_core/analysis/request/_work.py
cellprofiler_core-4.2.7.dist-info/LICENSE
cellprofiler_core-4.2.7.dist-info/METADATA
cellprofiler_core-4.2.7.dist-info/WHEEL
cellprofiler_core-4.2.7.dist-info/top_level.txt
cellprofiler_core-4.2.7.dist-info/RECORD
